kwldn_bot/__init__.py
kwldn_bot/bot.py
kwldn_bot/config.py
kwldn_bot/utils.py
kwldn_bot/database/__init__.py
kwldn_bot/database/types.py
kwldn_bot/modules/__init__.py
kwldn_bot/modules/error_handler.py
kwldn_bot/modules/state_clear.py
kwldn_bot-1.3.8.dist-info/METADATA
kwldn_bot-1.3.8.dist-info/WHEEL
kwldn_bot-1.3.8.dist-info/licenses/LICENSE
kwldn_bot-1.3.8.dist-info/RECORD
