Metadata-Version: 2.3
Name: kwldn_bot
Version: 1.3.8
Summary: Universal aiogram bot library
Project-URL: Homepage, https://github.com/kewldan/xbot
Author-email: kewldan <kewldanil1@gmail.com>
License: Copyright (c) 2024 Daniil Tenishev
License-File: LICENSE
Keywords: bot,telegram
Classifier: License :: OSI Approved :: MIT License
Classifier: Programming Language :: Python
Classifier: Programming Language :: Python :: 3
Requires-Python: >=3.12
Requires-Dist: aiogram
Requires-Dist: aiohttp
Requires-Dist: beanie
Requires-Dist: motor
Requires-Dist: pydantic
